shrike/__init__.py
shrike/_core/__init__.py
shrike/_core/eyesoff.py
shrike/_core/testing.py
shrike/_core/utils.py
shrike/build/__init__.py
shrike/build/commands/__init__.py
shrike/build/commands/prepare.py
shrike/build/commands/register.py
shrike/build/core/__init__.py
shrike/build/core/command_line.py
shrike/build/core/configuration.py
shrike/build/utils/__init__.py
shrike/build/utils/utils.py
shrike/compliant_logging/__init__.py
shrike/compliant_logging/argparser_utils.py
shrike/compliant_logging/constants.py
shrike/compliant_logging/data_conversions.py
shrike/compliant_logging/exceptions.py
shrike/compliant_logging/logging.py
shrike/compliant_logging/progress.py
shrike/compliant_logging/stack_trace_extractor.py
shrike/compliant_logging/system_info.py
shrike/distributed/__init__.py
shrike/distributed/cluster_auto_setup.py
shrike/distributed/dask.py
shrike/distributed/mpi_driver.py
shrike/distributed/ray.py
shrike/pipeline/__init__.py
shrike/pipeline/aml_connect.py
shrike/pipeline/argparser_utils.py
shrike/pipeline/canary_helper.py
shrike/pipeline/exceptions.py
shrike/pipeline/federated_learning.py
shrike/pipeline/module_helper.py
shrike/pipeline/module_helper_base.py
shrike/pipeline/pipeline_config.py
shrike/pipeline/pipeline_helper.py
shrike/pipeline/pipeline_helper_base.py
shrike/pipeline/ray_actor.py
shrike/pipeline/telemetry_utils.py
shrike/pipeline/components/fedavg/env.yaml
shrike/pipeline/components/fedavg/run.py
shrike/pipeline/components/fedavg/spec.yaml
shrike/pipeline/testing/__init__.py
shrike/pipeline/testing/components.py
shrike/pipeline/testing/importer.py
shrike/pipeline/testing/module_run_tests.py
shrike/pipeline/testing/pipeline_class_test.py
shrike/pipeline/testing/pipeline_class_test_v2.py
shrike/spark/__init__.py
shrike/spark/spark_net.py
shrike-2.0.2.dist-info/LICENSE
shrike-2.0.2.dist-info/METADATA
shrike-2.0.2.dist-info/NOTICE.txt
shrike-2.0.2.dist-info/WHEEL
shrike-2.0.2.dist-info/top_level.txt
shrike-2.0.2.dist-info/RECORD
