Metadata-Version: 2.1
Name: shrike
Version: 2.0.2
Summary: Python utilities for compliant Azure machine learning
Home-page: https://github.com/ai-platform-ml-platform/shrike
Author: AML Data Science
Author-email: aml-ds@microsoft.com
License: MIT
Classifier: License :: OSI Approved :: MIT License
Classifier: Programming Language :: Python :: 3
Classifier: Programming Language :: Python :: 3.8
Classifier: Programming Language :: Python :: 3.9
Classifier: Programming Language :: Python :: 3.10
Requires-Python: >=3.8
License-File: LICENSE
License-File: NOTICE.txt
Requires-Dist: azure-ai-ml>=1.23.1
Requires-Dist: ruamel.yaml~=0.16
Requires-Dist: tqdm>=4
Requires-Dist: mlflow
Requires-Dist: azureml-mlflow
Requires-Dist: scikit-learn
Requires-Dist: pandas
Requires-Dist: vaex-core
Requires-Dist: vaex
Provides-Extra: build
Requires-Dist: argparse-dataclass~=0.1; extra == "build"
Requires-Dist: omegaconf<2.2; extra == "build"
Requires-Dist: rsa~=4.7; extra == "build"
Requires-Dist: ruamel.yaml~=0.16; extra == "build"
Requires-Dist: semver~=2.13; extra == "build"
Requires-Dist: gitpython~=3.1; extra == "build"
Requires-Dist: jsonpath-ng~=1.5; extra == "build"
Requires-Dist: chardet~=4.0; extra == "build"
Requires-Dist: packaging>=20.0; extra == "build"
Requires-Dist: opencensus-ext-azure==1.0.7; extra == "build"
Requires-Dist: mldesigner[pipeline]>=0.1.0b16; extra == "build"
Requires-Dist: azure-core>=1.26.2; extra == "build"
Provides-Extra: dev
Requires-Dist: argparse-dataclass~=0.1; extra == "dev"
Requires-Dist: gitpython~=3.1; extra == "dev"
Requires-Dist: omegaconf~=2.0; extra == "dev"
Requires-Dist: rsa~=4.7; extra == "dev"
Requires-Dist: ruamel.yaml~=0.16; extra == "dev"
Requires-Dist: semver~=2.13; extra == "dev"
Requires-Dist: black~=24.4.2; extra == "dev"
Requires-Dist: flake8; extra == "dev"
Requires-Dist: typeguard; extra == "dev"
Requires-Dist: typing-extensions>=4.0; extra == "dev"
Requires-Dist: markdown-include==0.6.0; extra == "dev"
Requires-Dist: mkdocstrings-python-legacy==0.2.2; extra == "dev"
Requires-Dist: mkdocstrings==0.18.1; extra == "dev"
Requires-Dist: mkdocs-material==9.1.8; extra == "dev"
Requires-Dist: livereload==2.6.3; extra == "dev"
Requires-Dist: markdown==3.3.7; extra == "dev"
Requires-Dist: pytest; extra == "dev"
Requires-Dist: pytest-cov; extra == "dev"
Requires-Dist: pytest-order; extra == "dev"
Requires-Dist: blake3==0.4.1; extra == "dev"
Requires-Dist: twine~=3.3; extra == "dev"
Requires-Dist: wheel; extra == "dev"
Requires-Dist: pyspark==3.2.2; extra == "dev"
Requires-Dist: azure-mgmt-core; extra == "dev"
Provides-Extra: distributed
Requires-Dist: mpi4py>=3.1.3; extra == "distributed"
Requires-Dist: ray>=1.9.2; extra == "distributed"
Requires-Dist: dask[complete]>=2022.1.0; extra == "distributed"
Requires-Dist: protobuf>=3.19.5; extra == "distributed"
Provides-Extra: pipeline
Requires-Dist: gitpython~=3.1; extra == "pipeline"
Requires-Dist: hydra-core~=1.0.3; extra == "pipeline"
Requires-Dist: importlib-resources~=5.9.0; extra == "pipeline"
Requires-Dist: flatten-dict~=0.4; extra == "pipeline"
Requires-Dist: jsonpath-ng~=1.5; extra == "pipeline"
Requires-Dist: coolname~=1.1; extra == "pipeline"
Requires-Dist: omegaconf~=2.1.0; extra == "pipeline"
Requires-Dist: toposort~=1.7; extra == "pipeline"
Requires-Dist: opencensus-ext-azure==1.0.7; extra == "pipeline"
Requires-Dist: pytest; extra == "pipeline"
Requires-Dist: azure-ai-ml>=1.11.1; extra == "pipeline"
Requires-Dist: azure-identity; extra == "pipeline"
